{
  "persons": [
    { "id": "1", "firstName": "Marcel", "lastName": "Dupont", "birthDate": "1920-05-12", "birthPlace": "Lyon", "deathDate": "1998-11-23", "deathPlace": "Paris", "description": "L'arrière-grand-père, fondateur de l'entreprise familiale." },
    { "id": "2", "firstName": "Jean", "lastName": "Dupont", "birthDate": "1955-03-15", "birthPlace": "Paris", "deathDate": "2015-01-30", "deathPlace": "Paris", "description": "Fils aîné, passionné de jardinage et d'échecs." },
    { "id": "3", "firstName": "Sophie", "lastName": "Leclerc", "birthDate": "1958-07-22", "birthPlace": "Marseille", "deathDate": "2020-09-10", "deathPlace": "Marseille", "description": "Fille cadette, biologiste reconnue." },
    { "id": "4", "firstName": "Claire", "lastName": "Dupont", "birthDate": "1980-06-10", "birthPlace": "Paris", "deathDate": null, "deathPlace": null, "description": "Petite-fille aînée, ingénieure." },
    { "id": "5", "firstName": "Paul", "lastName": "Dupont", "birthDate": "1983-09-02", "birthPlace": "Paris", "deathDate": null, "deathPlace": null, "description": "Petit-fils cadet, musicien." },
    { "id": "6", "firstName": "Emma", "lastName": "Leclerc", "birthDate": "1985-11-15", "birthPlace": "Marseille", "deathDate": null, "deathPlace": null, "description": "Petite-fille, scientifique." },
    { "id": "7", "firstName": "Lucas", "lastName": "Dupont", "birthDate": "2010-04-20", "birthPlace": "Paris", "deathDate": null, "deathPlace": null, "description": "Arrière-petit-fils, étudiant." },
    { "id": "8", "firstName": "Chloé", "lastName": "Dupont", "birthDate": "2012-08-05", "birthPlace": "Paris", "deathDate": null, "deathPlace": null, "description": "Arrière-petite-fille, passionnée de dessin." },
    { "id": "9", "firstName": "Anne", "lastName": "Martin", "birthDate": "1956-04-12", "birthPlace": "Lyon", "deathDate": null, "deathPlace": null, "description": "Épouse de Jean Dupont." },
    { "id": "10", "firstName": "Marc", "lastName": "Leclerc", "birthDate": "1957-01-18", "birthPlace": "Marseille", "deathDate": null, "deathPlace": null, "description": "Époux de Sophie Leclerc." }
  ],
  "couples": [
    {
      "id": "c1",
      "partners": ["2", "9"],
      "children": ["4", "5"]
    },
    {
      "id": "c2",
      "partners": ["3", "10"],
      "children": ["6"]
    },
    {
      "id": "c3",
      "partners": ["1"],
      "children": ["2", "3"]
    }
  ]
}
